odoo/addons/helpdesk_mgmt_fieldservice/README.rst
odoo/addons/helpdesk_mgmt_fieldservice/__init__.py
odoo/addons/helpdesk_mgmt_fieldservice/__manifest__.py
odoo/addons/helpdesk_mgmt_fieldservice/i18n/ca.po
odoo/addons/helpdesk_mgmt_fieldservice/i18n/es.po
odoo/addons/helpdesk_mgmt_fieldservice/i18n/fr.po
odoo/addons/helpdesk_mgmt_fieldservice/i18n/helpdesk_mgmt_fieldservice.pot
odoo/addons/helpdesk_mgmt_fieldservice/i18n/pt_BR.po
odoo/addons/helpdesk_mgmt_fieldservice/models/__init__.py
odoo/addons/helpdesk_mgmt_fieldservice/models/fsm_location.py
odoo/addons/helpdesk_mgmt_fieldservice/models/fsm_order.py
odoo/addons/helpdesk_mgmt_fieldservice/models/helpdesk_ticket.py
odoo/addons/helpdesk_mgmt_fieldservice/readme/CONFIGURE.rst
odoo/addons/helpdesk_mgmt_fieldservice/readme/CONTRIBUTORS.rst
odoo/addons/helpdesk_mgmt_fieldservice/readme/DESCRIPTION.rst
odoo/addons/helpdesk_mgmt_fieldservice/readme/HISTORY.rst
odoo/addons/helpdesk_mgmt_fieldservice/readme/INSTALL.rst
odoo/addons/helpdesk_mgmt_fieldservice/readme/ROADMAP.rst
odoo/addons/helpdesk_mgmt_fieldservice/readme/USAGE.rst
odoo/addons/helpdesk_mgmt_fieldservice/security/ir.model.access.csv
odoo/addons/helpdesk_mgmt_fieldservice/static/description/icon.png
odoo/addons/helpdesk_mgmt_fieldservice/static/description/index.html
odoo/addons/helpdesk_mgmt_fieldservice/static/src/scss/helpdesk_column.scss
odoo/addons/helpdesk_mgmt_fieldservice/views/fsm_location_views.xml
odoo/addons/helpdesk_mgmt_fieldservice/views/fsm_order_views.xml
odoo/addons/helpdesk_mgmt_fieldservice/views/helpdesk_ticket_views.xml
odoo/addons/helpdesk_mgmt_fieldservice/views/res_partner.xml
odoo/addons/helpdesk_mgmt_fieldservice/wizards/__init__.py
odoo/addons/helpdesk_mgmt_fieldservice/wizards/fsm_order_close_wizard.py
odoo/addons/helpdesk_mgmt_fieldservice/wizards/fsm_order_close_wizard.xml
odoo12_addon_helpdesk_mgmt_fieldservice-12.0.1.1.0.dist-info/METADATA
odoo12_addon_helpdesk_mgmt_fieldservice-12.0.1.1.0.dist-info/WHEEL
odoo12_addon_helpdesk_mgmt_fieldservice-12.0.1.1.0.dist-info/top_level.txt
odoo12_addon_helpdesk_mgmt_fieldservice-12.0.1.1.0.dist-info/RECORD
