Metadata-Version: 2.1
Name: odoo12-addon-helpdesk-mgmt-fieldservice
Version: 12.0.1.1.0
Summary: Create service requests from a ticket
Home-page: https://github.com/OCA/helpdesk
Author: Open Source Integrators, Escodoo, Odoo Community Association (OCA)
Author-email: support@odoo-community.org
License: LGPL-3
Platform: UNKNOWN
Classifier: Programming Language :: Python
Classifier: Framework :: Odoo
Classifier: Framework :: Odoo :: 12.0
Classifier: License :: OSI Approved :: GNU Lesser General Public License v3 (LGPLv3)
Requires-Python: >=3.5
Requires-Dist: odoo12-addon-fieldservice
Requires-Dist: odoo12-addon-helpdesk-mgmt
Requires-Dist: odoo (<12.1dev,>=12.0a)
